gcp_cloud_storage_client_lib/__init__.py
gcp_cloud_storage_client_lib/mlops_gcp_client.py
gcp_storage_client-0.1.0.dist-info/METADATA
gcp_storage_client-0.1.0.dist-info/WHEEL
gcp_storage_client-0.1.0.dist-info/RECORD
