Metadata-Version: 2.1
Name: gcp-storage-client
Version: 0.1.0
Summary: Package for accessing into Cloud Storage in Google Cloud Platform.
Home-page: https://gitlab.com/jihoahn9303/mlops-library
License: Apache-2.0
Author: jihoahn9303
Author-email: rediate03@gmail.com
Requires-Python: >=3.9,<4.0
Classifier: License :: OSI Approved :: Apache Software License
Classifier: Programming Language :: Python :: 3
Classifier: Programming Language :: Python :: 3.9
Classifier: Programming Language :: Python :: 3.10
Classifier: Programming Language :: Python :: 3.11
Classifier: Programming Language :: Python :: 3.12
Requires-Dist: google-cloud-storage (>=2.14.0,<3.0.0)
Project-URL: Repository, https://gitlab.com/jihoahn9303/mlops-library
